README.rst
setup.py
django_url_migration.egg-info/PKG-INFO
django_url_migration.egg-info/SOURCES.txt
django_url_migration.egg-info/dependency_links.txt
django_url_migration.egg-info/requires.txt
django_url_migration.egg-info/top_level.txt
url_migration/__init__.py
url_migration/admin.py
url_migration/models.py
url_migration/views.py
url_migration/management/__init__.py
url_migration/management/commands/__init__.py
url_migration/management/commands/remove_expired_redirects.py
url_migration/migrations/0001_initial.py
url_migration/migrations/__init__.py
url_migration/tests/__init__.py
url_migration/tests/factories.py
url_migration/tests/test_commands.py
url_migration/tests/test_resolver.py
url_migration_demo/demo_application/__init__.py
url_migration_demo/demo_application/models.py
url_migration_demo/demo_application/views.py